setup.py
json_mapper/__init__.py
json_mapper/mapper.py
json_mapper/objects.py
json_mapper.egg-info/PKG-INFO
json_mapper.egg-info/SOURCES.txt
json_mapper.egg-info/dependency_links.txt
json_mapper.egg-info/not-zip-safe
json_mapper.egg-info/top_level.txt
tests/__init__.py
tests/tests.py